hdl/in_triangle.sv
module in_triangle(
    input clk_in,
    input rst_in,
    input wire [8:0] v1 [2:0],
    input wire [8:0] v2 [2:0],
    input wire [8:0] v3 [2:0],
    input wire [8:0] x,
    input wire [8:0] y,
    input wire valid_in,
    output logic in_tri,
    output logic valid_out
);

    enum {GET, DET, CALC} state;
    
    // vertices w sign
    logic signed [9:0] vert1 [2:0];
    logic signed [9:0] vert2 [2:0];
    logic signed [9:0] vert3 [2:0];

    assign vert1[0] = {1'b0, v1[0]};
    assign vert1[1] = {1'b0, v1[1]};
    assign vert1[2] = {1'b0, v1[2]};
    assign vert2[0] = {1'b0, v2[0]};
    assign vert2[1] = {1'b0, v2[1]};
    assign vert2[2] = {1'b0, v2[2]};
    assign vert3[0] = {1'b0, v3[0]};
    assign vert3[1] = {1'b0, v3[1]};
    assign vert3[2] = {1'b0, v3[2]};

    // column vectors : msb = x, lsb = y
    logic signed [9:0] vect1 [1:0];
    logic signed [9:0] vect2 [1:0];
    logic signed [9:0] v0 [1:0];
    logic signed [9:0] v [1:0];

    assign v0[1] = vert1[2];
    assign v0[0] = vert1[1];
    assign vect1[1] = vert2[2]-vert1[2];
    assign vect1[0] = vert2[1]-vert1[1];
    assign vect2[1] = vert3[2]-vert1[2];
    assign vect2[0] = vert3[1]-vert1[1];
    assign v[1] = x;
    assign v[0] = y;

    // determinants
    logic signed [16:0] detv1v2;
    logic signed [16:0] detvv2;
    logic signed [16:0] detv0v2;
    logic signed [16:0] detvv1;
    logic signed [16:0] detv0v1;

    // assign detv1v2 = vect1[1]*vect2[0] - vect1[0]*vect2[1];
    // assign detvv2 = v[1]*vect2[0] - v[0]*vect2[1];
    // assign detv0v2 = v0[1]*vect2[0] - v0[0]*vect2[1];
    // assign detvv1 = v[1]*vect1[0] - v[0]*vect1[1];
    // assign detv0v1 = v0[1]*vect1[0] - v0[0]*vect1[1];

    // numerators
    logic signed [16:0] a_num;
    logic signed [16:0] b_num;

    assign a_num = detvv2 - detv0v2;
    assign b_num = detvv1 - detv0v1;

    logic [15:0] a_raw;
    logic [15:0] b_raw;
    logic [15:0] det_raw;
    // assign a_raw = (a_num[16])? -a_num[15:0]: a_num[15:0];
    // assign b_raw = (b_num[16])? -b_num[15:0]: b_num[15:0];
    // assign det_raw = (detv1v2[16])? -detv1v2[15:0]: detv1v2[15:0];

    // output signals
    logic a;
    logic b;

    assign a = ((~(detv1v2[16] ^ a_num[16])) & (a_raw <= det_raw)) | !a_raw;
    assign b = ((detv1v2[16] ^ b_num[16]) & (b_raw <= det_raw)) | !b_raw;

    // assign in_tri = a & b & (a_num[15:0] < det_raw - b_raw);

    always_ff @(posedge clk_in) begin
        if (rst_in) begin
            valid_out <= 0;
            in_tri <= 0;
        end else begin
            case (state)
                GET: begin 
                    if (valid_in) begin
                        detv1v2 <= vect1[1]*vect2[0] - vect1[0]*vect2[1];
                        detvv2 <= v[1]*vect2[0] - v[0]*vect2[1];
                        detv0v2 <= v0[1]*vect2[0] - v0[0]*vect2[1];
                        detvv1 <= v[1]*vect1[0] - v[0]*vect1[1];
                        detv0v1 <= v0[1]*vect1[0] - v0[0]*vect1[1];
                        state <= DET;
                    end
                    valid_out <= 0;
                    in_tri <= 0;
                end
                DET: begin
                    // a_num = detvv2 - detv0v2;
                    // b_num = detvv1 - detv0v1;
                    a_raw = (a_num[16])? -a_num[15:0]: a_num[15:0];
                    b_raw = (b_num[16])? -b_num[15:0]: b_num[15:0];
                    det_raw = (detv1v2[16])? -detv1v2[15:0]: detv1v2[15:0];
                    state <= CALC;
                end
                CALC: begin
                    in_tri <= (((~(detv1v2[16] ^ a_num[16])) & (a_raw <= det_raw)) | !a_raw) &
                                (((detv1v2[16] ^ b_num[16]) & (b_raw <= det_raw)) | !b_raw) & (a_raw + b_raw <= det_raw);
                    valid_out <= 1;
                    state <= GET;
                end
                    // in_tri <= a & b & (a_raw + b_raw <= det_raw);
                    // valid_out <= 1;
            endcase;
        end
    end

endmodule

sim/in_triangle_tb.sv
`timescale 1ns / 1ps
`default_nettype none

module in_triangle_tb;

    logic clk;
    logic rst;
    logic [8:0] v1 [2:0];
    logic [8:0] v2 [2:0];
    logic [8:0] v3 [2:0];
    logic [8:0] x;
    logic [8:0] y;
    logic valid_in;
    logic in_tri;
    logic valid_out;

    in_triangle uut (
        .clk_in(clk),
        .rst_in(rst),
        .v1(v1),
        .v2(v2),
        .v3(v3),
        .x(x),
        .y(y),
        .valid_in(valid_in),
        .in_tri(in_tri),
        .valid_out(valid_out)
    );

    always begin
        clk = !clk;
        #5;
    end

    initial begin
        $dumpfile("in_triangle_tb.vcd"); //file to store value change dump (vcd)
        $dumpvars(0,in_triangle_tb);
        $display("Starting Sim"); //print nice message at start
        clk = 0;
        rst = 0;
        #5;
        rst = 1;
        #10;
        rst = 0;
        #5;
        v1[2] = 2;
        v1[1] = 4;
        v2[2] = 4;
        v2[1] = 1;
        v3[2] = 0;
        v3[1] = 0;
        for (integer i=0;i<=4;i=i+1) begin
            for (integer j=0;j<=4;j=j+1) begin
                x = i;
                y = j;
                valid_in = 1;
                #10;
                valid_in = 0;
                #10;
            end
        end
        #100;
        $display("Finishing Sim");
        $finish;
    end

endmodule

`default_nettype wire

in_triangle_tb.vcd
$date
	Mon Dec  4 21:27:57 2023
$end
$version
	Icarus Verilog
$end
$timescale
	1ps
$end
$scope module in_triangle_tb $end
$var wire 1 ! valid_out $end
$var wire 1 " in_tri $end
$var reg 1 # clk $end
$var reg 1 $ rst $end
$var reg 1 % valid_in $end
$var reg 9 & x [8:0] $end
$var reg 9 ' y [8:0] $end
$scope module uut $end
$var wire 1 ( a $end
$var wire 1 ) b $end
$var wire 1 # clk_in $end
$var wire 1 $ rst_in $end
$var wire 1 % valid_in $end
$var wire 9 * x [8:0] $end
$var wire 9 + y [8:0] $end
$var wire 17 , detvv2 [16:0] $end
$var wire 17 - detvv1 [16:0] $end
$var wire 17 . detv1v2 [16:0] $end
$var wire 17 / detv0v2 [16:0] $end
$var wire 17 0 detv0v1 [16:0] $end
$var wire 16 1 det_raw [15:0] $end
$var wire 16 2 b_raw [15:0] $end
$var wire 17 3 b_num [16:0] $end
$var wire 16 4 a_raw [15:0] $end
$var wire 17 5 a_num [16:0] $end
$var reg 1 " in_tri $end
$var reg 1 ! valid_out $end
$upscope $end
$scope begin $ivl_for_loop0 $end
$var integer 32 6 i [31:0] $end
$scope begin $ivl_for_loop1 $end
$var integer 32 7 j [31:0] $end
$upscope $end
$upscope $end
$upscope $end
$enddefinitions $end
$comment Show the parameter values. $end
$dumpall
$end
#0
$dumpvars
bx 7
bx 6
bx 5
bx 4
bx 3
bx 2
bx 1
bx 0
bx /
bx .
bx -
bx ,
bx +
bx *
x)
x(
bx '
bx &
x%
0$
0#
x"
x!
$end
#5000
0"
0!
1$
1#
#10000
0#
#15000
1#
0$
#20000
1(
1)
b0 4
b1110 2
b1110 1
0#
1%
b0 5
b0 ,
b1110 3
b0 -
b0 '
b0 +
b0 &
b0 *
b0 7
b0 6
b11111111111110010 .
b0 /
b11111111111110010 0
#25000
1!
1"
1#
#30000
0#
0%
#35000
0"
0!
1#
#40000
0(
b10 4
b1100 2
0#
1%
b10 5
b10 ,
b1100 3
b11111111111111110 -
b1 '
b1 +
b1 7
#45000
1!
1#
#50000
0#
0%
#55000
0!
1#
#60000
b100 4
b1010 2
0#
1%
b100 5
b100 ,
b1010 3
b11111111111111100 -
b10 '
b10 +
b10 7
#65000
1!
1#
#70000
0#
0%
#75000
0!
1#
#80000
b110 4
b1000 2
0#
1%
b110 5
b110 ,
b1000 3
b11111111111111010 -
b11 '
b11 +
b11 7
#85000
1!
1#
#90000
0#
0%
#95000
0!
1#
#100000
b1000 4
b110 2
0#
1%
b1000 5
b1000 ,
b110 3
b11111111111111000 -
b100 '
b100 +
b100 7
#105000
1!
1#
#110000
0#
0%
#115000
0!
1#
#120000
1(
b100 4
b1011 2
0#
1%
b0 '
b0 +
b11111111111111100 5
b11111111111111100 ,
b1011 3
b11111111111111101 -
b1 &
b1 *
b1 6
b0 7
#125000
1!
1#
#130000
0#
0%
#135000
0!
1#
#140000
b10 4
b1001 2
0#
1%
b11111111111111110 5
b11111111111111110 ,
b1001 3
b11111111111111011 -
b1 '
b1 +
b1 7
#145000
1!
1"
1#
#150000
0#
0%
#155000
0"
0!
1#
#160000
b0 4
b111 #160000
b0 5
b0 ,
b111 3
b11111111111111001 -
b10 '
b10 +
b10 7
#165000
1!
1"
1#
#170000
0#
0%
#175000
0"
0!
1#
#180000
0(
b10 4
b101 2
0#
1%
b10 5
b10 ,
b101 3
b11111111111110111 -
b11 '
b11 +
b11 7
#185000
1!
1#
#190000
0#
0%
#195000
0!
1#
#200000
b100 4
b11 2
0#
1%
b100 5
b100 ,
b11 3
b11111111111110101 -
b100 '
b100 +
b100 7
#205000
1!
1#
#210000
0#
0%
#215000
0!
1#
#220000
1(
b1000 4
b1000 2
0#
1%
b0 '
b0 +
b11111111111111000 5
b11111111111111000 ,
b1000 3
b11111111111111010 -
b10 &
b10 *
b10 6
b0 7
#225000
1!
1#
#230000
0#
0%
#235000
0!
1#
#240000
b110 4
b110 2
0#
1%
b11111111111111010 5
b11111111111111010 ,
b110 3
b11111111111111000 -
b1 '
b1 +
b1 7
#245000
1!
1"
1#
#250000
0#
0%
#255000
0"
0!
1#
#260000
b100 4
b100 2
0#
1%
b11111111111111100 5
b11111111111111100 ,
b100 3
b11111111111110110 -
b10 '
b10 +
b10 7
#265000
1!
1"
1#
#270000
0#
0%
#275000
0"
0!
1#
#280000
b10 4
b10 2
0#
1%
b11111111111111110 5
b11111111111111110 ,
b10 3
b11111111111110100 -
b11 '
b11 +
b11 7
#285000
1!
1"
1#
#290000
0#
0%
#295000
0"
0!
1#
#300000
b0 4
b0 2
0#
1%
b0 5
b0 ,
b0 3
b11111111111110010 -
b100 '
b100 +
b100 7
#305000
1!
1"
1#
#310000
0#
0%
#315000
0"
0!
1#
#320000
1(
b1100 4
b101 2
0#
1%
b0 '
b0 +
b11111111111110100 5
b11111111111110100 ,
b101 3
b11111111111110111 -
b11 &
b11 *
b11 6
b0 7
#325000
1!
1#
#330000
0#
0%
#335000
0!
1#
#340000
b1010 4
b11 2
0#
1%
b11111111111110110 5
b11111111111110110 ,
b11 3
b11111111111110101 -
b1 '
b1 +
b1 7
#345000
1!
1"
1#
#350000
0#
0%
#355000
0"
0!
1#
#360000
b1000 4
b1 2
0#
1%
b11111111111111000 5
b11111111111111000 ,
b1 3
b11111111111110011 -
b10 '
b10 +
b10 7
#365000
1!
1"
1#
#370000
0#
0%
#375000
0"
0!
1#
#380000
0)
b110 4
0#
1%
b11111111111111010 5
b11111111111111010 ,
b11111111111111111 3
b11111111111110001 -
b11 '
b11 +
b11 7
#385000
1!
1#
#390000
0#
0%
#395000
0!
1#
#400000
b100 4
b11 2
0#
1%
b11111111111111100 5
b11111111111111100 ,
b11111111111111101 3
b11111111111101111 -
b100 '
b100 +
b100 7
#405000
1!
1#
#410000
0#
0%
#415000
0!
1#
#420000
1)
0(
b10000 4
b10 2
0#
1%
b0 '
b0 +
b11111111111110000 5
b11111111111110000 ,
b10 3
b11111111111110100 -
b100 &
b100 *
b100 6
b0 7
#425000
1!
1#
#430000
0#
0%
#435000
0!
1#
#440000
1(
b1110 4
b0 2
0#
1%
b11111111111110010 5
b11111111111110010 ,
b0 3
b11111111111110010 -
b1 '
b1 +
b1 7
#445000
1!
1"
1#
#450000
0#
0%
#455000
0"
0!
1#
#460000
0)
b1100 4
b10 2
0#
1%
b11111111111110100 5
b11111111111110100 ,
b11111111111111110 3
b11111111111110000 -
b10 '
b10 +
b10 7
#465000
1!
1#
#470000
0#
0%
#475000
0!
1#
#480000
b1010 4
b100 2
0#
1%
b11111111111110110 5
b11111111111110110 ,
b11111111111111100 3
b11111111111101110 -
b11 '
b11 +
b11 7
#485000
1!
1#
#490000
0#
0%
#495000
0!
1#
#500000
b1000 4
b110 2
0#
1%
b11111111111111000 5
b11111111111111000 ,
b11111111111111010 3
b11111111111101100 -
b100 '
b100 +
b100 7
#505000
1!
1#
#510000
0#
0%
#515000
0!
1#
#520000
0#
b101 6
b101 7
